r<?xml version="1.0" encoding="UTF-8" standalone="yes"?> 
<channels>
<channels_info>
<title>TV XXX</title>
<thumbnail></thumbnail>
<fanart></fanart>
</channels_info>

<item>
<title>[COLOR yellow]SEXY SAT TV[/COLOR]</title>
<link>rtmp://81.89.48.215/xxxsexysat/xxxsexysat.stream_360p</link>
<thumbnail>http://upload.wikimedia.org/wikipedia/en/0/0b/Sexy_Sat_TV_logo.jpg</thumbnail>
</item>

<item>
<title>[COLOR yellow]CAM PLAY[/COLOR]</title>
<link>http://playback.d2see.com:1935/wavemachine-live01/_definst_/mp4:playboytv_channel2/playlist.m3u8</link>
<thumbnail>http://www.vecinitasxxx.com/wp-content/uploads/2012/08/Increible-vecinita-culona-e.jpg</thumbnail>
</item>

<item>
<title>[COLOR yellow]VISIT X[/COLOR]</title>
<link>rtsp://194.116.150.47:1935/live/visitx.stream1</link>
<thumbnail>http://4.bp.blogspot.com/-4vMMQXPEI9A/USo2off5yLI/AAAAAAAARCA/Ygw1YcxSFtE/s400/matches+today.jpg</thumbnail>
</item>

<item>
<title>[COLOR yellow]LIVE CHAT[/COLOR]</title>
<link>rtsp://81.89.48.215:1935/xyz777wkz/xy_360p</link>
<thumbnail>http://www.xxxlivewebcams.com/img/webcams-header.jpg</thumbnail>
</item>

<item>
<title>[COLOR yellow]BELLA LUZ TV[/COLOR]</title>
<link>http://46.249.213.87/iPhone/broadcast/bellaluz-tablet.3gp.m3u8</link>
<thumbnail>http://tecnofanatico.com/wp-content/uploads/2011/09/XXX-dominio.jpg</thumbnail>
</item>

<item>
<title>[COLOR yellow]SEXY TV[/COLOR]</title>
<link>rtsp://85.12.5.8:1935/aovivo/sexprive</link>
<thumbnail>http://1.bp.blogspot.com/-kj1fmJKpRco/T46dMBs3i6I/AAAAAAAAEKo/LcSXmg3gIUA/s1600/Sexy+Hot+2.png</thumbnail>
</item>

<item>
<title>[COLOR yellow]BRASILEÑAS [/COLOR]</title>
<link>rtmp://edge-05.livestreamcast.org/Brasileirinhas/Brasileirinhas/ playpath=Brasileirinhas swfUrl=http://livestreamcast.org/jwplayer/jwplayer.flash.swf live=1 pageUrl=http://livestreamcast.org/embed.php?c=brasileirinhas&vw=100%&vh=100%</link>
<thumbnail>http://fotospornox.com/uploads/brasileas_en_la_playa_desnudas_8278133105.jpg</thumbnail>
</item>

<item>
<title>[COLOR yellow]SEX ZONE [/COLOR]</title>
<link>rtmp://edge-05.livestreamcast.org/sexzonehd/sexzonehd/ playpath=sexzonehd swfUrl=http://livestreamcast.org/jwplayer/jwplayer.flash.swf live=1 pageUrl=http://livestreamcast.org/embed.php?c=sexzonehd&vh=100%&vw=100%</link>
<thumbnail>http://cdn.koimoi.com/wp-content/new-galleries/2013/02/X-Zone-Zee-TV.jpg</thumbnail>
</item>

<item>
<title>[COLOR yellow]VENUS[/COLOR]</title>
<link>rtmp://207.244.67.22/iguide playpath=ii09ho91721568x swfUrl=http://cdn1.iguide.to/player/secure_player_iguide_embed_token.swf live=1 pageUrl=http://www.iguide.to/embedplayer_new.php?width=489&height=370&channel=2190&autoplay=true token=#ed%h0#w18623jsda6523lDGD</link>
<thumbnail>http://2.bp.blogspot.com/-wLjGZ2YOUxw/UQ1mR7CyGYI/AAAAAAAAAnI/2G37Zcj3VJo/s1600/venus.jpg</thumbnail>
</item>

<item>
<title>[COLOR yellow]PLAYBOY TV[/COLOR]</title>
<link>rtmp://edge-05.livestreamcast.org:1935/pboytv/pboytv swfUrl=
http://livestreamcast.org/StrobeMediaPlayback.swf live=1 pageUrl=http://livestreamcast.org/embed.php?
c=pboytv&vw=460&vh=360</link>
<thumbnail>http://findlogo.net/images/P/playboy%20tv%20logo.jpg</thumbnail>
</item>

<item>
<title>[COLOR yellow]HOT[/COLOR]</title>
<link>rtmp://109.123.126.66/live playpath=vvenus?id=67043 swfUrl=http://www.ucaster.eu/static/scripts/fplayer.swf live=1 pageUrl=http://www.ucaster.eu/embedded/vvenus/1/480/380 conn=S:OK</link>
<thumbnail>http://www.wtvision.com/files/img/news/hotgold.jpg</thumbnail>
</item>

<item>
<title>[COLOR yellow]DESIRE TV[/COLOR]</title>
<link>http://artm:artm@84.22.33.24:8060</link>
<thumbnail>http://es.kingofsat.net/jpg/desire.jpg</thumbnail>
</item>

<item>
<title>[COLOR yellow]BRAZZERS TV[/COLOR]</title>
<link>http://195.154.188.161/hls/sexy.m3u8</link>
<thumbnail>http://satcesc.com/web/wp-content/uploads/2014/02/brazzers-tv-europe1.jpg</thumbnail>
</item>

<item>
<title>[COLOR yellow]MILF TV[/COLOR]</title>
<link>rtmp://live190.la3.origin.filmon.com:8086/live/247.high.stream</link>
<thumbnail>http://gamblersmeantime.com/wp-content/uploads/2012/03/milf_horny-milf-ready-to-fuck.jpg</thumbnail>
</item>

<item>
<title>[COLOR yellow]BLACK TV[/COLOR]</title>
<link>rtmp://live190.la3.origin.filmon.com:8086/live/244.high.stream</link>
<thumbnail>http://content.wafflegirl.com/galleries/gthumb/0/322/322627_3c0d581_770x2000.jpg</thumbnail>
</item>

<item>
<title>[COLOR yellow]BLACK 2 TV[/COLOR]</title>
<link>rtmp://live190.la3.origin.filmon.com:8086/live/245.high.stream</link>
<thumbnail>http://media.cuckold69.com/galleries/1206/120625-black-fucking-white-women-in-hotel-room-pictures.jpg</thumbnail>
</item>

<item>
<title>[COLOR yellow]GAY TV[/COLOR]</title>
<link>rtmp://live190.la3.origin.filmon.com:8086/live/73.high.stream</link>
<thumbnail>http://upload.wikimedia.org/wikipedia/commons/3/3f/GAY_tv_Logo.png</thumbnail>
</item>

<item>
<title>[COLOR yellow]SHEMALE TV[/COLOR]</title>
<link>rtmp://live190.la3.origin.filmon.com:8086/live/246.high.stream</link>
<thumbnail>http://fap.to/images/49/632659550/amateur-porn/The-most-beautiful-Brazilian-shemales-part-5-cock-1.jpg</thumbnail>
</item>

<item>
<title>[COLOR yellow]ASIAN TV[/COLOR]</title>
<link>rtmp://live190.la3.origin.filmon.com:8086/live/198.high.stream</link>
<thumbnail>http://content.wafflegirl.com/galleries/gthumb/0/350/350225_a2258ea_770x2000.jpg</thumbnail>
</item>

<item>
<title>[COLOR yellow][/COLOR]</title>
<link></link>
<thumbnail></thumbnail>
</item>

<item>
<title>[COLOR yellow][/COLOR]</title>
<link></link>
<thumbnail></thumbnail>
</item>

<item>
<title>[COLOR yellow][/COLOR]</title>
<link></link>
<thumbnail></thumbnail>
</item>
